simplifine_alpha/__init__.py
simplifine_alpha/annotation.py
simplifine_alpha/eval.py
simplifine_alpha/inference_tools.py
simplifine_alpha/logger.py
simplifine_alpha/train_engine.py
simplifine_alpha/train_engine_client.py
simplifine_alpha/train_utils.py
simplifine_alpha/url_class.py
simplifine_alpha/utils.py
simplifine_alpha/tests/__init__.py
simplifine_alpha/tests/test.py
simplifine_alpha-0.0.81.dist-info/METADATA
simplifine_alpha-0.0.81.dist-info/WHEEL
simplifine_alpha-0.0.81.dist-info/licenses/LICENSE
simplifine_alpha-0.0.81.dist-info/RECORD
