Metadata-Version: 2.3
Name: simplifine-alpha
Version: 0.0.81
Summary: An easy to use, open-source LLM finetuning library that handles all the complexities of the process for you.
Project-URL: Homepage, https://github.com/simplifine-llm/Simplifine
Project-URL: Issues, https://github.com/simplifine-llm/Simplifine/issues
Author-email: "Ali Kavoosi, Raveen Kariyawasam" <founders@simplfine.com>
License-File: LICENSE
Classifier: License :: OSI Approved :: GNU General Public License v3 (GPLv3)
Classifier: Operating System :: OS Independent
Classifier: Programming Language :: Python :: 3
Requires-Python: >=3.10
Requires-Dist: accelerate
Requires-Dist: datasets
Requires-Dist: deepspeed
Requires-Dist: numpy
Requires-Dist: openai
Requires-Dist: peft
Requires-Dist: pypdf2
Requires-Dist: requests
Requires-Dist: scikit-learn
Requires-Dist: sentence-transformers
Requires-Dist: setuptools
Requires-Dist: torch
Requires-Dist: tqdm
Requires-Dist: transformers
Requires-Dist: trl
Requires-Dist: wandb
